esrrtdisplay01/__init__.py
esrrtdisplay01/esrrtdisplay01.py
esrrtdisplay01/simmessages.py
quakesrrtdisplay_tspspi-0.0.13a0.dist-info/LICENSE.md
quakesrrtdisplay_tspspi-0.0.13a0.dist-info/METADATA
quakesrrtdisplay_tspspi-0.0.13a0.dist-info/WHEEL
quakesrrtdisplay_tspspi-0.0.13a0.dist-info/entry_points.txt
quakesrrtdisplay_tspspi-0.0.13a0.dist-info/top_level.txt
quakesrrtdisplay_tspspi-0.0.13a0.dist-info/RECORD
