Metadata-Version: 2.1
Name: quakesrrtdisplay-tspspi
Version: 0.0.13a0
Summary: A simple realtime display for QUAK/ESR data in a specific experimental setup
Home-page: https://github.com/tspspi/quakesrrtdisplay
Author: Thomas Spielauer
Author-email: pypipackages01@tspi.at
Classifier: Programming Language :: Python :: 3
Classifier: License :: OSI Approved :: BSD License
Classifier: Operating System :: OS Independent
Requires-Python: >=3.6
License-File: LICENSE.md
Requires-Dist: paho-mqtt>=1.6.1
Requires-Dist: matplotlib>=3.3.4
Requires-Dist: FreeSimpleGUI>=5.1.0
